setup.cfg
setup.py
bkmaker/__init__.py
bkmaker/bkmaker.py
bkmaker.egg-info/PKG-INFO
bkmaker.egg-info/SOURCES.txt
bkmaker.egg-info/dependency_links.txt
bkmaker.egg-info/entry_points.txt
bkmaker.egg-info/requires.txt
bkmaker.egg-info/top_level.txt