Metadata-Version: 1.1
Name: bkmaker
Version: 0.0.3
Summary: backup your schema from RDS directly to S3
Home-page: https://github.com/bjtox/bkmaker.git
Author: Antonio Bitonti
Author-email: antonio.bitonti@gmail.com
License: MIT
Keywords: aws rds backup schema mysql
Platform: UNKNOWN
Classifier: Development Status :: 4 - Beta
Classifier: License :: OSI Approved :: MIT License
Classifier: Programming Language :: Python :: 2.7
